{
    "global": {
      "base-black": {
        "value": "#0e0e0e",
        "type": "color"
      },
      "grey-600": {
        "value": "#333333",
        "type": "color"
      },
      "base-white": {
        "value": "#ffffff",
        "type": "color"
      },
      "grey-800": {
        "value": "#1d1d1d",
        "type": "color"
      },
      "grey-300": {
        "value": "#474747",
        "type": "color"
      },
      "grey-100": {
        "value": "#c9c9c9",
        "type": "color"
      },
      "fontFamilies": {
        "sf-pro-display": {
          "value": "SF Pro Display",
          "type": "fontFamilies"
        }
      },
      "lineHeights": {
        "0": {
          "value": "AUTO",
          "type": "lineHeights"
        }
      },
      "fontWeights": {
        "sf-pro-display-0": {
          "value": "Regular",
          "type": "fontWeights"
        },
        "sf-pro-display-1": {
          "value": "Light Italic",
          "type": "fontWeights"
        }
      },
      "fontSize": {
        "0": {
          "value": "10",
          "type": "fontSizes"
        },
        "1": {
          "value": "12",
          "type": "fontSizes"
        },
        "2": {
          "value": "14",
          "type": "fontSizes"
        }
      },
      "letterSpacing": {
        "0": {
          "value": "5%",
          "type": "letterSpacing"
        },
        "1": {
          "value": "0%",
          "type": "letterSpacing"
        }
      },
      "paragraphSpacing": {
        "0": {
          "value": "0",
          "type": "paragraphSpacing"
        }
      },
      "action-button-label-1": {
        "value": {
          "fontFamily": "{fontFamilies.sf-pro-display}",
          "fontWeight": "{fontWeights.sf-pro-display-0}",
          "lineHeight": "{lineHeights.0}",
          "fontSize": "{fontSize.0}",
          "letterSpacing": "{letterSpacing.0}",
          "paragraphSpacing": "{paragraphSpacing.0}",
          "paragraphIndent": "{paragraphIndent.0}",
          "textCase": "{textCase.none}",
          "textDecoration": "{textDecoration.none}"
        },
        "type": "typography"
      },
      "form-label-1": {
        "value": {
          "fontFamily": "{fontFamilies.sf-pro-display}",
          "fontWeight": "{fontWeights.sf-pro-display-0}",
          "lineHeight": "{lineHeights.0}",
          "fontSize": "{fontSize.1}",
          "letterSpacing": "{letterSpacing.1}",
          "paragraphSpacing": "{paragraphSpacing.0}",
          "paragraphIndent": "{paragraphIndent.0}",
          "textCase": "{textCase.none}",
          "textDecoration": "{textDecoration.none}"
        },
        "type": "typography"
      },
      "mini-pub-title-1": {
        "value": {
          "fontFamily": "{fontFamilies.sf-pro-display}",
          "fontWeight": "{fontWeights.sf-pro-display-0}",
          "lineHeight": "{lineHeights.0}",
          "fontSize": "{fontSize.2}",
          "letterSpacing": "{letterSpacing.1}",
          "paragraphSpacing": "{paragraphSpacing.0}",
          "paragraphIndent": "{paragraphIndent.0}",
          "textCase": "{textCase.none}",
          "textDecoration": "{textDecoration.none}"
        },
        "type": "typography"
      },
      "mini-pub-desc-1": {
        "value": {
          "fontFamily": "{fontFamilies.sf-pro-display}",
          "fontWeight": "{fontWeights.sf-pro-display-1}",
          "lineHeight": "{lineHeights.0}",
          "fontSize": "{fontSize.0}",
          "letterSpacing": "{letterSpacing.1}",
          "paragraphSpacing": "{paragraphSpacing.0}",
          "paragraphIndent": "{paragraphIndent.0}",
          "textCase": "{textCase.none}",
          "textDecoration": "{textDecoration.none}"
        },
        "type": "typography"
      },
      "form-text-input-1": {
        "value": {
          "fontFamily": "{fontFamilies.sf-pro-display}",
          "fontWeight": "{fontWeights.sf-pro-display-0}",
          "lineHeight": "{lineHeights.0}",
          "fontSize": "{fontSize.2}",
          "letterSpacing": "{letterSpacing.0}",
          "paragraphSpacing": "{paragraphSpacing.0}",
          "paragraphIndent": "{paragraphIndent.0}",
          "textCase": "{textCase.none}",
          "textDecoration": "{textDecoration.none}"
        },
        "type": "typography"
      },
      "textCase": {
        "none": {
          "value": "none",
          "type": "textCase"
        }
      },
      "textDecoration": {
        "none": {
          "value": "none",
          "type": "textDecoration"
        }
      }
    }
  }